pybiz/__init__.py
pybiz/constants.py
pybiz/dirty.py
pybiz/exc.py
pybiz/logging.py
pybiz/manifest.py
pybiz/predicate.py
pybiz/schema.py
pybiz/api/__init__.py
pybiz/api/async_server_registry.py
pybiz/api/cli_registry.py
pybiz/api/exc.py
pybiz/api/repl_registry.py
pybiz/api/middleware/__init__.py
pybiz/api/middleware/base.py
pybiz/api/middleware/http_session_middleware.py
pybiz/api/middleware/guard_middleware/__init__.py
pybiz/api/middleware/guard_middleware/argument_specification.py
pybiz/api/middleware/guard_middleware/guard.py
pybiz/api/middleware/guard_middleware/guard_middleware.py
pybiz/api/registry/__init__.py
pybiz/api/registry/registry.py
pybiz/api/registry/registry_argument_loader.py
pybiz/api/registry/registry_decorator.py
pybiz/api/registry/registry_proxy.py
pybiz/api/web/__init__.py
pybiz/api/web/graphql.py
pybiz/api/web/http_registry.py
pybiz/api/web/http_server_registry.py
pybiz/api/web/websocket_server_registry.py
pybiz/api/web/wsgi_service_registry.py
pybiz/biz/__init__.py
pybiz/biz/biz_list.py
pybiz/biz/biz_object.py
pybiz/biz/components/__init__.py
pybiz/biz/components/recursive_list.py
pybiz/biz/components/session.py
pybiz/biz/components/user.py
pybiz/biz/internal/__init__.py
pybiz/biz/internal/biz_object_type_builder.py
pybiz/biz/internal/dump.py
pybiz/biz/internal/field_property.py
pybiz/biz/internal/query.py
pybiz/biz/internal/relationship_property.py
pybiz/biz/internal/save.py
pybiz/biz/relationship/__init__.py
pybiz/biz/relationship/behavior.py
pybiz/biz/relationship/relationship.py
pybiz/contrib/__init__.py
pybiz/contrib/falcon/__init__.py
pybiz/contrib/falcon/constants.py
pybiz/contrib/falcon/exceptions.py
pybiz/contrib/falcon/media.py
pybiz/contrib/falcon/registry.py
pybiz/contrib/falcon/resource.py
pybiz/contrib/grpc/__init__.py
pybiz/contrib/grpc/grpc_client.py
pybiz/contrib/grpc/registry/__init__.py
pybiz/contrib/grpc/registry/grpc_registry.py
pybiz-0.1.dist-info/METADATA
pybiz-0.1.dist-info/RECORD
pybiz-0.1.dist-info/WHEEL
pybiz-0.1.dist-info/top_level.txt
