Metadata-Version: 2.1
Name: pybiz
Version: 0.1
Summary: Pybiz.
Home-page: https://github.com/gigaquads/pybiz.git
Author: Gigaquads
Author-email: notdsk@gmail.com
License: UNKNOWN
Platform: UNKNOWN
Classifier: Programming Language :: Python :: 3
Classifier: License :: OSI Approved :: MIT License
Requires-Dist: appyratus
Requires-Dist: python-dateutil
Requires-Dist: pytz
Requires-Dist: venusian
Requires-Dist: pyyaml
Requires-Dist: graphql-py
Requires-Dist: requests
Requires-Dist: pycrypto
Requires-Dist: google
Requires-Dist: protobuf
Requires-Dist: grpcio
Requires-Dist: grpcio-tools
Requires-Dist: btrees
Requires-Dist: falcon
Requires-Dist: websockets
Requires-Dist: pytest
Requires-Dist: mock
